qwork/__init__.py
qwork/fileitem.py
qwork/icon_rc.py
qwork/qreplaces.py
qwork/qtclrs.py
qwork/qtimp.py
qwork/utils.py
qwork/workspace.py
qwork-0.0.5.dist-info/METADATA
qwork-0.0.5.dist-info/WHEEL
qwork-0.0.5.dist-info/top_level.txt
qwork-0.0.5.dist-info/RECORD
