Metadata-Version: 2.1
Name: qwork
Version: 0.0.5
Summary: ...
Author-email: 2229066748@qq.com
Maintainer: Eagle'sBaby
Maintainer-email: 2229066748@qq.com
License: Apache Licence 2.0
Keywords: pyqt
Classifier: Programming Language :: Python :: 3
Classifier: Operating System :: Microsoft :: Windows
Requires-Python: >=3
Requires-Dist: pyqt5>=5.15
Requires-Dist: files3>=0.9
